LICENSE
MANIFEST.in
README.rst
setup.py
bin/rump
bin/rumpd
rump/__init__.py
rump/cli.py
rump/exc.py
rump/request.py
rump/rule.py
rump/settings.py
rump/upstream.py
rump/wsgi.py
rump.egg-info/PKG-INFO
rump.egg-info/SOURCES.txt
rump.egg-info/dependency_links.txt
rump.egg-info/requires.txt
rump.egg-info/top_level.txt
rump/exp/__init__.py
rump/exp/types.py
rump/parser/__init__.py
rump/parser/match.py
rump/parser/rule.py
rump/parser/upstream.py
rump/router/__init__.py
rump/router/etcd.py
rump/router/redis.py
rump/router/zookeeper.py
test/test_cli.py
test/test_exp.py
test/test_extension.py
test/test_request.py
test/test_router.py
test/test_rules.py
test/test_settings.py
test/test_upstream.py
test/test_wsgi.py