Metadata-Version: 1.0
Name: rump
Version: 0.2.1
Summary: Upstream selection.
Home-page: https://github.com/bninja/rump/
Author: Rump Us
Author-email: ru@mp.us
License: MIT
Platform: any
Classifier: Development Status :: 4 - Beta
Classifier: Intended Audience :: Developers
Classifier: Natural Language :: English
Classifier: License :: OSI Approved :: ISC License (ISCL)
Classifier: Programming Language :: Python
Classifier: Programming Language :: Python :: 2.7
